{"url": "https://www.yelp.com/biz/escape-travel-phillip?adjust_creative=92p07_JjKyriZTQxAXRiKQ&utm_campaign=yelp_api_v3&utm_medium=api_v3_business_lookup&utm_source=92p07_JjKyriZTQxAXRiKQ", "id": "escape-travel-phillip", "rating": 0.0, "location": {"zip_code": "2606", "address2": null, "country": "AU", "state": "ACT", "city": "Phillip", "address1": "Keltie St", "address3": null}, "name": "Escape Travel", "term": "hotels", "phone": "+611300735865", "coordinates": {"longitude": 149.0847015, "latitude": -35.3454208}, "photos": [], "categories": [{"alias": "travelservices", "title": "Travel Services"}], "is_closed": false, "image_url": "", "review_count": 0, "is_claimed": false}