{"pub_date": "2016-03-13T00:00:00Z", "subsection_name": "Horse Racing", "lead_paragraph": "Candy led all the way to win the $400,000 San Felipe Stakes for 3-year-olds by two lengths, upsetting the favorite Mor Spirit in a Kentucky Derby prep race at Santa Anita in Arcadia, Calif.", "print_page": "10", "document_type": "article", "byline": {"person": [], "original": "By THE ASSOCIATED PRESS", "organization": "THE ASSOCIATED PRESS"}, "multimedia": [], "section_name": "Sports", "headline": {"content_kicker": "Sports Briefing | Horse Racing", "print_headline": "Danzing Candy Zips to Upset", "main": "Danzing Candy Zips to Upset at San Felipe Stakes"}, "source": "The New York Times", "blog": [], "word_count": "83", "web_url": "http://www.nytimes.com/2016/03/13/sports/horse-racing/danzing-candy-zips-to-upset-at-san-felipe-stakes.html", "slideshow_credits": null, "news_desk": "Sports", "type_of_material": "Brief", "snippet": "Candy led all the way to win the $400,000 San Felipe Stakes for 3-year-olds by two lengths, upsetting the favorite Mor Spirit in a Kentucky Derby prep race at Santa Anita in Arcadia, Calif.", "_id": "56e4fead38f0d83a21f5becc", "abstract": null, "keywords": [{"rank": "1", "name": "subject", "value": "Horse Racing", "is_major": "N"}, {"rank": "2", "name": "glocations", "value": "Arcadia (Calif)", "is_major": "N"}]}