{"coordinates": {"longitude": 149.0971375, "latitude": -35.4066505}, "review_count": 0, "categories": [{"title": "Tours", "alias": "tours"}], "url": "https://www.yelp.com/biz/monaro-coaches-erindale-centre?adjust_creative=92p07_JjKyriZTQxAXRiKQ&utm_campaign=yelp_api_v3&utm_medium=api_v3_business_lookup&utm_source=92p07_JjKyriZTQxAXRiKQ", "name": "Monaro Coaches", "term": "hotels", "rating": 0.0, "photos": ["https://s3-media2.fl.yelpcdn.com/bphoto/l_QI5QrJxfzNdXvi4LbjtQ/o.jpg", "https://s3-media2.fl.yelpcdn.com/bphoto/gt5_4UzDAUL0ShV7Cvj7wA/o.jpg", "https://s3-media2.fl.yelpcdn.com/bphoto/zTqy0kQqGEUh-nU_zuWrVA/o.jpg"], "is_closed": false, "is_claimed": false, "phone": "+61261616300", "id": "monaro-coaches-erindale-centre", "location": {"address2": null, "address3": null, "zip_code": "2903", "country": "AU", "address1": "", "state": "ACT", "city": "Erindale Centre"}, "image_url": "https://s3-media2.fl.yelpcdn.com/bphoto/l_QI5QrJxfzNdXvi4LbjtQ/o.jpg"}