{"location": {"address3": "", "address1": "Old Spitalfields Market", "country": "GB", "state": "XGL", "zip_code": "E1 6BG", "address2": "Brushfield Street", "city": "London"}, "id": "rainforest-creations-london", "price": "\u00a3", "review_count": 8, "photos": ["https://s3-media3.fl.yelpcdn.com/bphoto/vbgTbId6HOFxcNpHfErbVg/o.jpg", "https://s3-media3.fl.yelpcdn.com/bphoto/XUdI4lg8dLukCFP6qYHcOg/o.jpg"], "is_claimed": true, "rating": 5.0, "is_closed": false, "image_url": "https://s3-media3.fl.yelpcdn.com/bphoto/vbgTbId6HOFxcNpHfErbVg/o.jpg", "name": "Rainforest Creations", "categories": [{"title": "Cafes", "alias": "cafes"}], "coordinates": {"latitude": 51.519707057572, "longitude": -0.0754371031798655}, "term": "restaurants", "phone": "+447985235219", "url": "https://www.yelp.com/biz/rainforest-creations-london?adjust_creative=92p07_JjKyriZTQxAXRiKQ&utm_campaign=yelp_api_v3&utm_medium=api_v3_business_lookup&utm_source=92p07_JjKyriZTQxAXRiKQ"}