{"location": {"address3": "", "address1": "61 Rupert Street", "country": "GB", "state": "XGL", "zip_code": "W1D 7PL", "address2": "", "city": "London"}, "id": "spuntino-london", "price": "\u00a3\u00a3", "hours": [{"is_open_now": false, "hours_type": "REGULAR", "open": [{"start": "1200", "end": "0000", "is_overnight": false, "day": 0}, {"start": "1200", "end": "0000", "is_overnight": false, "day": 1}, {"start": "1200", "end": "0000", "is_overnight": false, "day": 2}, {"start": "1200", "end": "0100", "is_overnight": true, "day": 3}, {"start": "1200", "end": "0100", "is_overnight": true, "day": 4}, {"start": "1200", "end": "0100", "is_overnight": true, "day": 5}, {"start": "1200", "end": "2300", "is_overnight": false, "day": 6}]}], "review_count": 100, "photos": ["https://s3-media4.fl.yelpcdn.com/bphoto/pnGN8PrlMiYtnonIiC4WQw/o.jpg", "https://s3-media4.fl.yelpcdn.com/bphoto/WLMbySqCV83x02axVtUULg/o.jpg", "https://s3-media3.fl.yelpcdn.com/bphoto/JE9wOrsbiHeUwHrk7tbkqQ/o.jpg"], "is_claimed": false, "rating": 4.0, "is_closed": false, "image_url": "https://s3-media4.fl.yelpcdn.com/bphoto/pnGN8PrlMiYtnonIiC4WQw/o.jpg", "name": "Spuntino", "categories": [{"title": "Tapas/Small Plates", "alias": "tapasmallplates"}], "coordinates": {"latitude": 51.5121469, "longitude": -0.1338562}, "term": "restaurants", "phone": "", "url": "https://www.yelp.com/biz/spuntino-london?adjust_creative=92p07_JjKyriZTQxAXRiKQ&utm_campaign=yelp_api_v3&utm_medium=api_v3_business_lookup&utm_source=92p07_JjKyriZTQxAXRiKQ"}