{"location": {"address3": "", "address1": "34 Holland Road", "country": "GB", "state": "XGL", "zip_code": "W14 8BA", "address2": "", "city": "London"}, "id": "the-crown-and-sceptre-london-2", "price": "\u00a3\u00a3", "hours": [{"is_open_now": false, "hours_type": "REGULAR", "open": [{"start": "0730", "end": "2330", "is_overnight": false, "day": 0}, {"start": "0730", "end": "2330", "is_overnight": false, "day": 1}, {"start": "0730", "end": "2330", "is_overnight": false, "day": 2}, {"start": "0730", "end": "2330", "is_overnight": false, "day": 3}, {"start": "0730", "end": "2330", "is_overnight": false, "day": 4}, {"start": "0730", "end": "2330", "is_overnight": false, "day": 5}, {"start": "0730", "end": "2330", "is_overnight": false, "day": 6}]}], "review_count": 9, "photos": ["https://s3-media2.fl.yelpcdn.com/bphoto/SrqVnwmQAzEfpt_RpK9LkQ/o.jpg", "https://s3-media3.fl.yelpcdn.com/bphoto/Uz-_f3zbimcDGGVoH-IB5w/o.jpg", "https://s3-media3.fl.yelpcdn.com/bphoto/lBVZEH4xhJKlz-Qt93nrDA/o.jpg"], "is_claimed": true, "rating": 4.0, "is_closed": false, "image_url": "https://s3-media3.fl.yelpcdn.com/bphoto/SrqVnwmQAzEfpt_RpK9LkQ/o.jpg", "name": "The Crown and Sceptre", "categories": [{"title": "Gastropubs", "alias": "gastropubs"}], "coordinates": {"latitude": 51.4979662, "longitude": -0.20744}, "term": "restaurants", "phone": "+442076032007", "url": "https://www.yelp.com/biz/the-crown-and-sceptre-london-2?adjust_creative=92p07_JjKyriZTQxAXRiKQ&utm_campaign=yelp_api_v3&utm_medium=api_v3_business_lookup&utm_source=92p07_JjKyriZTQxAXRiKQ"}