{"_id": "53332d8338f0d87e2de04877", "print_page": null, "blog": [], "byline": {"person": [], "organization": "REUTERS", "original": "By REUTERS"}, "multimedia": [], "source": "Reuters", "type_of_material": "News", "news_desk": null, "snippet": "Following are brief profiles of the 15 American League (AL) teams ahead of the 2014 Major League Baseball season:...", "document_type": "article", "subsection_name": "Baseball", "word_count": "1134", "headline": {"print_headline": "Profiles of American League Teams", "main": "Profiles of American League Teams"}, "lead_paragraph": "Following are brief profiles of the 15 American League (AL) teams ahead of the 2014 Major League Baseball season:", "slideshow_credits": null, "keywords": [], "pub_date": "2014-03-26T15:39:04Z", "section_name": "Sports", "abstract": null, "web_url": "http://www.nytimes.com/reuters/2014/03/26/sports/baseball/26reuters-baseball-penpix-american.html"}