{"_id": "54428a0c38f0d811e19d77ea", "print_page": null, "blog": [], "byline": {"person": [], "organization": "REUTERS", "original": "By REUTERS"}, "multimedia": [], "source": "Reuters", "type_of_material": "News", "news_desk": "None", "snippet": "The apprentice made the sorcerer fight all the way before top seed Henrik Stenson scrambled a two-hole victory over fellow Swede Jonas Blixt at the Volvo World Match Play Championship on Saturday....", "document_type": "article", "subsection_name": "Golf", "word_count": "580", "headline": {"print_headline": "Stenson Battles Past Tenacious Blixt to Reach Semis", "main": "Stenson Battles Past Tenacious Blixt to Reach Semis"}, "lead_paragraph": "The apprentice made the sorcerer fight all the way before top seed Henrik Stenson scrambled a two-hole victory over fellow Swede Jonas Blixt at the Volvo World Match Play Championship on Saturday.", "slideshow_credits": null, "keywords": [], "pub_date": "2014-10-18T11:39:29Z", "section_name": "Sports", "abstract": null, "web_url": "http://www.nytimes.com/reuters/2014/10/18/sports/golf/18reuters-golf-european.html"}