{"url": "https://www.yelp.com/biz/guylian-belgium-chocolate-cafe-sydney-2?adjust_creative=92p07_JjKyriZTQxAXRiKQ&utm_campaign=yelp_api_v3&utm_medium=api_v3_business_lookup&utm_source=92p07_JjKyriZTQxAXRiKQ", "id": "guylian-belgium-chocolate-cafe-sydney-2", "location": {"state": "NSW", "zip_code": "2000", "address2": "1-25 Harbour St", "country": "AU", "city": "Sydney", "address3": "", "address1": "TR5/TR6"}, "rating": 2.5, "photos": ["https://s3-media1.fl.yelpcdn.com/bphoto/NB33vjtvjM2KYJwrJTz5LQ/o.jpg", "https://s3-media4.fl.yelpcdn.com/bphoto/5KDI6973IToCDhMaSuoVbA/o.jpg", "https://s3-media2.fl.yelpcdn.com/bphoto/pFetccVPBRuVyypbHGqkGw/o.jpg"], "name": "Guylian Belgium Chocolate  Cafe", "term": "restaurants", "phone": "+61292831947", "hours": [{"is_open_now": true, "open": [{"is_overnight": false, "end": "0000", "start": "0800", "day": 0}, {"is_overnight": false, "end": "0000", "start": "0800", "day": 1}, {"is_overnight": false, "end": "0000", "start": "0800", "day": 2}, {"is_overnight": false, "end": "0000", "start": "0800", "day": 3}, {"is_overnight": false, "end": "0000", "start": "0800", "day": 4}, {"is_overnight": false, "end": "0000", "start": "0800", "day": 5}, {"is_overnight": false, "end": "0000", "start": "0800", "day": 6}], "hours_type": "REGULAR"}], "coordinates": {"longitude": 151.20095, "latitude": -33.8752}, "categories": [{"alias": "chocolate", "title": "Chocolatiers & Shops"}, {"alias": "venues", "title": "Venues & Event Spaces"}, {"alias": "cafes", "title": "Cafes"}], "is_closed": false, "image_url": "https://s3-media3.fl.yelpcdn.com/bphoto/NB33vjtvjM2KYJwrJTz5LQ/o.jpg", "price": "$$", "review_count": 19, "is_claimed": false}