{"pub_date": "2016-03-16T00:00:00Z", "subsection_name": null, "lead_paragraph": "Senator Dianne Feinstein discusses the role of website in facilitating the sex trade of children.", "print_page": "22", "document_type": "article", "byline": [], "multimedia": [], "section_name": "Opinion", "headline": {"content_kicker": "Letter", "print_headline": "Human Trafficking", "main": "Human Trafficking", "kicker": "Letter"}, "source": "The New York Times", "blog": [], "word_count": "191", "web_url": "http://www.nytimes.com/2016/03/16/opinion/human-trafficking.html", "slideshow_credits": null, "news_desk": "Letters", "type_of_material": "Letter", "snippet": "Senator Dianne Feinstein discusses the role of website in facilitating the sex trade of children.", "_id": "56e853be38f0d85c820e6323", "abstract": "Letter from Sen Dianne Feinstein responds to March 10 column by Nicholas Kristof denouncing websites like Backpage.com for facilitating sex trafficking of minors.", "keywords": [{"rank": "2", "name": "subject", "value": "Sex Crimes", "is_major": "Y"}, {"rank": "3", "name": "subject", "value": "Child Abuse and Neglect", "is_major": "Y"}, {"rank": "4", "name": "subject", "value": "Prostitution", "is_major": "Y"}, {"rank": "5", "name": "subject", "value": "Human Trafficking", "is_major": "Y"}, {"rank": "6", "name": "persons", "value": "Feinstein, Dianne", "is_major": "N"}, {"rank": "7", "name": "subject", "value": "Law and Legislation", "is_major": "N"}]}