{"pub_date": "2016-06-02T00:00:00Z", "subsection_name": null, "lead_paragraph": "A reader faults the United Nations for deleting a chapter about damage to the Great Barrier Reef from a U.N. report.", "print_page": "22", "document_type": "article", "byline": [], "multimedia": [], "section_name": "Opinion", "headline": {"content_kicker": "Letter", "print_headline": "U.N. Hypocrisy on Climate", "main": "U.N. Hypocrisy on a Climate Report", "kicker": "Letter"}, "source": "The New York Times", "blog": [], "word_count": "124", "web_url": "http://www.nytimes.com/2016/06/02/opinion/un-hypocrisy-on-a-climate-report.html", "slideshow_credits": null, "news_desk": "Letters", "type_of_material": "Letter", "snippet": "A reader faults the United Nations for deleting a chapter about damage to the Great Barrier Reef from a U.N. report.", "_id": "574f276238f0d84d6030922d", "abstract": null, "keywords": [{"rank": "1", "name": "glocations", "value": "Great Barrier Reef (Australia)", "is_major": "N"}, {"rank": "2", "name": "subject", "value": "Global Warming", "is_major": "N"}, {"rank": "3", "name": "organizations", "value": "United Nations", "is_major": "N"}]}