{"pub_date": "2016-11-18T19:42:07Z", "subsection_name": null, "lead_paragraph": "The Center for Medicare Advocacy calls privatization \u201ca very bad deal for the 55 million older and disabled people who rely on Medicare.\u201d", "print_page": "22", "document_type": "article", "byline": [], "multimedia": [], "section_name": "Opinion", "headline": {"content_kicker": "Letter", "print_headline": "Privatizing Medicare", "main": "Privatizing Medicare", "kicker": "Letter"}, "source": "The New York Times", "blog": [], "word_count": "98", "web_url": "http://www.nytimes.com/2016/11/19/opinion/privatizing-medicare.html", "slideshow_credits": null, "news_desk": "Letters", "type_of_material": "Letter", "snippet": "The Center for Medicare Advocacy calls privatization \u201ca very bad deal for the 55 million older and disabled people who rely on Medicare.\u201d...", "_id": "582f59987c459f6a5fcced75", "abstract": null, "keywords": [{"rank": "1", "name": "subject", "value": "Medicare", "is_major": "N"}, {"rank": "2", "name": "subject", "value": "Health Insurance and Managed Care", "is_major": "N"}]}