{"pub_date": "2016-01-03T00:00:00Z", "subsection_name": "Weddings", "lead_paragraph": "The couple, who met at the University of Wisconsin, work in San Diego.", "print_page": "11", "document_type": "article", "byline": [], "multimedia": [], "section_name": "Fashion & Style", "headline": {"print_headline": "Danielle D\u2019Agostino,  Ethan Schmidt", "main": "Danielle D\u2019Agostino, Ethan Schmidt"}, "source": "The New York Times", "blog": [], "word_count": "220", "web_url": "http://www.nytimes.com/2016/01/03/fashion/weddings/danielle-dagostino-ethan-schmidt.html", "slideshow_credits": null, "news_desk": "Society", "type_of_material": "News", "snippet": "The couple, who met at the University of Wisconsin, work in San Diego.", "_id": "5688ae5d38f0d81904703968", "abstract": null, "keywords": [{"rank": "1", "name": "subject", "value": "Weddings and Engagements", "is_major": "N"}]}