{"_id": "52ffa8af38f0d8295c4a2140", "print_page": null, "blog": [], "byline": {"person": [], "organization": "REUTERS", "original": "By REUTERS"}, "multimedia": [], "source": "Reuters", "type_of_material": "News", "news_desk": null, "snippet": "\"I only drink mine,\" Edik Baturin warns when talk turns to samogon, a potent, chest-warming moonshine he brews in his shack in the shadow of the Caucasus mountains....", "document_type": "article", "subsection_name": "Europe", "word_count": "806", "headline": {"print_headline": "Life Has Changed but at Least There's Samogon", "main": "Life Has Changed but at Least There's Samogon"}, "lead_paragraph": "\"I only drink mine,\" Edik Baturin warns when talk turns to samogon, a potent, chest-warming moonshine he brews in his shack in the shadow of the Caucasus mountains.", "slideshow_credits": null, "keywords": [], "pub_date": "2014-02-15T12:47:40Z", "section_name": "World", "abstract": null, "web_url": "http://www.nytimes.com/reuters/2014/02/15/world/europe/15reuters-olympics-samogon.html"}