{"_id": "548e1b0138f0d8437a5db7af", "print_page": null, "blog": [], "byline": {"person": [], "organization": "THE ASSOCIATED PRESS", "original": "By THE ASSOCIATED PRESS"}, "multimedia": [], "source": "AP", "type_of_material": "News", "news_desk": "None", "snippet": "Rescue crews in Nicaragua have found a fishing boat that capsized in the Caribbean last week with 50 people aboard and are searching for 18 crew members who remain missing, authorities said Sunday....", "document_type": "article", "subsection_name": "Americas", "word_count": "388", "headline": {"print_headline": "Nicaragua Rescue Crews Find Capsized Boat", "main": "Nicaragua Rescue Crews Find Capsized Boat"}, "lead_paragraph": "Rescue crews in Nicaragua have found a fishing boat that capsized in the Caribbean last week with 50 people aboard and are searching for 18 crew members who remain missing, authorities said Sunday.", "slideshow_credits": null, "keywords": [], "pub_date": "2014-12-14T18:15:37Z", "section_name": "World", "abstract": null, "web_url": "http://www.nytimes.com/aponline/2014/12/14/world/americas/ap-lt-nicaragua-shipwreck.html"}