{"url": "https://www.yelp.com/biz/chili-verde-denver-2?adjust_creative=92p07_JjKyriZTQxAXRiKQ&utm_campaign=yelp_api_v3&utm_medium=api_v3_business_lookup&utm_source=92p07_JjKyriZTQxAXRiKQ", "id": "chili-verde-denver-2", "location": {"state": "CO", "zip_code": "80211", "address2": "", "country": "US", "city": "Denver", "address3": "", "address1": "2311 Federal Blvd"}, "rating": 4.5, "photos": ["https://s3-media1.fl.yelpcdn.com/bphoto/bI1sB94bOnHXJYp4H3I9IQ/o.jpg", "https://s3-media1.fl.yelpcdn.com/bphoto/BfPWo58IR8t4QS1nK4TEOg/o.jpg", "https://s3-media4.fl.yelpcdn.com/bphoto/zILJ4anLTfFBQ675p58mqA/o.jpg"], "name": "Chili Verde", "term": "restaurants", "phone": "+17202872296", "hours": [{"is_open_now": false, "open": [{"is_overnight": false, "end": "2100", "start": "1100", "day": 1}, {"is_overnight": false, "end": "2100", "start": "1100", "day": 2}, {"is_overnight": false, "end": "2200", "start": "1100", "day": 3}, {"is_overnight": false, "end": "2200", "start": "1100", "day": 4}, {"is_overnight": false, "end": "2200", "start": "1100", "day": 5}, {"is_overnight": false, "end": "2100", "start": "1100", "day": 6}], "hours_type": "REGULAR"}], "coordinates": {"longitude": -105.025296, "latitude": 39.7514521}, "categories": [{"alias": "mexican", "title": "Mexican"}], "is_closed": false, "image_url": "https://s3-media4.fl.yelpcdn.com/bphoto/bI1sB94bOnHXJYp4H3I9IQ/o.jpg", "price": "$$", "review_count": 240, "is_claimed": true}