{"location": {"address3": "", "address1": "Clevedon Showgrounds", "country": "NZ", "state": "AUK", "zip_code": "2582", "address2": "Monument Road", "city": "Auckland"}, "rating": 5.0, "price": "$", "hours": [{"is_open_now": false, "hours_type": "REGULAR", "open": [{"start": "0830", "end": "1200", "is_overnight": false, "day": 6}]}], "review_count": 5, "photos": ["https://s3-media1.fl.yelpcdn.com/bphoto/tody-L4t9m5jjqo20CmCVQ/o.jpg", "https://s3-media3.fl.yelpcdn.com/bphoto/tYiXkJScJ1Rx1Ir0QWiLeA/o.jpg", "https://s3-media4.fl.yelpcdn.com/bphoto/OWXauDJBaSNmvRMh4szJXQ/o.jpg"], "is_claimed": false, "id": "clevedon-farmers-market-auckland", "is_closed": false, "image_url": "https://s3-media1.fl.yelpcdn.com/bphoto/tody-L4t9m5jjqo20CmCVQ/o.jpg", "name": "Clevedon Farmers Market", "coordinates": {"latitude": -37.0167743, "longitude": 175.0482804}, "categories": [{"title": "Farmers Market", "alias": "farmersmarket"}, {"title": "Local Flavor", "alias": "localflavor"}, {"title": "Food Stands", "alias": "foodstands"}], "term": "attractions", "phone": "+6492676800", "url": "https://www.yelp.com/biz/clevedon-farmers-market-auckland?adjust_creative=92p07_JjKyriZTQxAXRiKQ&utm_campaign=yelp_api_v3&utm_medium=api_v3_business_lookup&utm_source=92p07_JjKyriZTQxAXRiKQ"}