{"location": {"address3": "", "address1": "3700 Michigan Ave", "country": "US", "state": "MI", "zip_code": "48216", "address2": "", "city": "Detroit"}, "id": "mikes-famous-ham-place-detroit", "price": "$", "hours": [{"is_open_now": false, "hours_type": "REGULAR", "open": [{"start": "0700", "end": "1500", "is_overnight": false, "day": 0}, {"start": "0700", "end": "1500", "is_overnight": false, "day": 1}, {"start": "0700", "end": "1500", "is_overnight": false, "day": 2}, {"start": "0700", "end": "1500", "is_overnight": false, "day": 3}, {"start": "0700", "end": "1500", "is_overnight": false, "day": 4}, {"start": "0700", "end": "1500", "is_overnight": false, "day": 5}]}], "review_count": 42, "photos": ["https://s3-media1.fl.yelpcdn.com/bphoto/9k-2L52SXD8IEgsA4Xk4eg/o.jpg", "https://s3-media2.fl.yelpcdn.com/bphoto/Vc-sOdU8ujLKsXZfFf79MQ/o.jpg", "https://s3-media1.fl.yelpcdn.com/bphoto/Uu0NUogTVWTkbzAhXAe7Nw/o.jpg"], "is_claimed": true, "rating": 4.5, "is_closed": false, "image_url": "https://s3-media2.fl.yelpcdn.com/bphoto/9k-2L52SXD8IEgsA4Xk4eg/o.jpg", "name": "Mike's Famous Ham Place", "categories": [{"title": "Sandwiches", "alias": "sandwiches"}, {"title": "Delis", "alias": "delis"}], "coordinates": {"latitude": 42.3315353, "longitude": -83.0948029}, "term": "restaurants", "phone": "+13138946922", "url": "https://www.yelp.com/biz/mikes-famous-ham-place-detroit?adjust_creative=92p07_JjKyriZTQxAXRiKQ&utm_campaign=yelp_api_v3&utm_medium=api_v3_business_lookup&utm_source=92p07_JjKyriZTQxAXRiKQ"}