{"coordinates": {"longitude": -74.00351, "latitude": 40.71931}, "review_count": 5, "categories": [{"alias": "theater", "title": "Performing Arts"}], "url": "https://www.yelp.com/biz/soho-repertory-theatre-new-york-2?adjust_creative=92p07_JjKyriZTQxAXRiKQ&utm_campaign=yelp_api_v3&utm_medium=api_v3_business_lookup&utm_source=92p07_JjKyriZTQxAXRiKQ", "name": "Soho Repertory Theatre", "term": "attractions", "rating": 4.5, "photos": ["https://s3-media2.fl.yelpcdn.com/bphoto/xWlUEiufeohP-YDp3K1Wgw/o.jpg"], "is_closed": false, "is_claimed": true, "phone": "+12129418632", "image_url": "https://s3-media4.fl.yelpcdn.com/bphoto/xWlUEiufeohP-YDp3K1Wgw/o.jpg", "location": {"address2": "", "address3": "", "city": "New York", "country": "US", "address1": "46 Walker St", "state": "NY", "zip_code": "10013"}, "id": "soho-repertory-theatre-new-york-2"}