{"coordinates": {"longitude": -73.9845962524414, "latitude": 40.751191}, "review_count": 34, "hours": [{"is_open_now": true, "open": [{"is_overnight": false, "end": "0000", "start": "0000", "day": 0}, {"is_overnight": false, "end": "0000", "start": "0000", "day": 1}, {"is_overnight": false, "end": "0000", "start": "0000", "day": 2}, {"is_overnight": false, "end": "0000", "start": "0000", "day": 3}, {"is_overnight": false, "end": "0000", "start": "0000", "day": 4}, {"is_overnight": false, "end": "0000", "start": "0000", "day": 5}, {"is_overnight": false, "end": "0000", "start": "0000", "day": 6}], "hours_type": "REGULAR"}], "categories": [{"alias": "hotels", "title": "Hotels"}], "url": "https://www.yelp.com/biz/springhill-suites-new-york-midtown-manhattan-fifth-avenue-new-york?adjust_creative=92p07_JjKyriZTQxAXRiKQ&utm_campaign=yelp_api_v3&utm_medium=api_v3_business_lookup&utm_source=92p07_JjKyriZTQxAXRiKQ", "name": "SpringHill Suites New York Midtown Manhattan/Fifth Avenue", "term": "attractions", "rating": 4.0, "photos": ["https://s3-media2.fl.yelpcdn.com/bphoto/cmwQ8IAMOppwng47QhOMYA/o.jpg"], "is_closed": false, "is_claimed": true, "phone": "+12123912255", "image_url": "https://s3-media1.fl.yelpcdn.com/bphoto/cmwQ8IAMOppwng47QhOMYA/o.jpg", "location": {"address2": "", "address3": "", "city": "New York", "country": "US", "address1": "25 West 37th St", "state": "NY", "zip_code": "10018"}, "price": "$$", "id": "springhill-suites-new-york-midtown-manhattan-fifth-avenue-new-york"}