{"location": {"address3": null, "address1": "Canberra Airport", "country": "AU", "state": "ACT", "zip_code": "2601", "address2": null, "city": "Canberra"}, "rating": 0.0, "review_count": 0, "is_closed": false, "is_claimed": false, "id": "chocks-away-canberra", "photos": [], "image_url": "", "name": "Chocks Away", "categories": [{"title": "Transportation", "alias": "transport"}], "coordinates": {"latitude": -35.3151093, "longitude": 149.130188}, "term": "hotels", "phone": "", "url": "https://www.yelp.com/biz/chocks-away-canberra?adjust_creative=92p07_JjKyriZTQxAXRiKQ&utm_campaign=yelp_api_v3&utm_medium=api_v3_business_lookup&utm_source=92p07_JjKyriZTQxAXRiKQ"}