{"coordinates": {"longitude": 115.8599319, "latitude": -31.9543781}, "review_count": 3, "categories": [{"title": "Cafes", "alias": "cafes"}, {"title": "Specialty Food", "alias": "gourmet"}], "url": "https://www.yelp.com/biz/david-jones-foodhall-perth?adjust_creative=92p07_JjKyriZTQxAXRiKQ&utm_campaign=yelp_api_v3&utm_medium=api_v3_business_lookup&utm_source=92p07_JjKyriZTQxAXRiKQ", "name": "David Jones Foodhall", "term": "restaurants", "rating": 4.5, "photos": ["https://s3-media3.fl.yelpcdn.com/bphoto/0x2ErGnJdbV9kEBotiHiyQ/o.jpg", "https://s3-media2.fl.yelpcdn.com/bphoto/npOWXnI5JXsgTwSrRNZcQA/o.jpg", "https://s3-media3.fl.yelpcdn.com/bphoto/iB3Qu5Go4ZwUCCJnkpIXPg/o.jpg"], "is_closed": false, "is_claimed": false, "phone": "+61892104000", "image_url": "https://s3-media3.fl.yelpcdn.com/bphoto/0x2ErGnJdbV9kEBotiHiyQ/o.jpg", "location": {"city": "Perth", "address2": "622 Hay St", "address3": "", "zip_code": "6000", "address1": "Level 1, David Jones", "state": "WA", "country": "AU"}, "price": "$$", "id": "david-jones-foodhall-perth"}