{"coordinates": {"longitude": -0.1013116, "latitude": 51.5046768}, "review_count": 5, "categories": [{"alias": "gyms", "title": "Gyms"}], "url": "https://www.yelp.com/biz/fitness4less-southwark-london?adjust_creative=92p07_JjKyriZTQxAXRiKQ&utm_campaign=yelp_api_v3&utm_medium=api_v3_business_lookup&utm_source=92p07_JjKyriZTQxAXRiKQ", "name": "Fitness4Less Southwark", "term": "attractions", "rating": 4.5, "photos": ["https://s3-media1.fl.yelpcdn.com/bphoto/4PSwdrOktdIcRRf2fyRd5A/o.jpg"], "is_closed": false, "is_claimed": false, "phone": "", "image_url": "https://s3-media2.fl.yelpcdn.com/bphoto/4PSwdrOktdIcRRf2fyRd5A/o.jpg", "location": {"address2": "Southwark", "address3": "", "city": "London", "country": "GB", "address1": "23-29 Great Suffolk Street", "state": "XGL", "zip_code": "SE1 0UE"}, "id": "fitness4less-southwark-london"}