{"url": "https://www.yelp.com/biz/serrarao-fine-foods-and-italian-pantry-north-hobart?adjust_creative=92p07_JjKyriZTQxAXRiKQ&utm_campaign=yelp_api_v3&utm_medium=api_v3_business_lookup&utm_source=92p07_JjKyriZTQxAXRiKQ", "id": "serrarao-fine-foods-and-italian-pantry-north-hobart", "rating": 0.0, "location": {"zip_code": "7000", "address2": null, "country": "AU", "state": "TAS", "city": "North Hobart", "address1": "34 Federal St", "address3": null}, "name": "Serrarao Fine Foods & Italian Pantry", "term": "hotels", "phone": "+61362312788", "coordinates": {"longitude": 147.31843, "latitude": -42.87005}, "photos": [], "categories": [{"alias": "hotels", "title": "Hotels"}], "is_closed": false, "image_url": "", "review_count": 0, "is_claimed": false}