{"pub_date": "2016-06-01T00:00:00Z", "subsection_name": null, "lead_paragraph": "In the South Bronx, the arrival of two high-end coffee shops sparks debate over gentrification.", "print_page": null, "document_type": "multimedia", "byline": [], "multimedia": [{"width": 190, "height": 126, "url": "images/2016/06/01/dining/01BRONX-slide-EAFR/01BRONX-slide-EAFR-thumbWide.jpg", "subtype": "wide", "legacy": {"wide": "images/2016/06/01/dining/01BRONX-slide-EAFR/01BRONX-slide-EAFR-thumbWide.jpg", "widewidth": "190", "wideheight": "126"}, "type": "image"}, {"width": 600, "height": 401, "url": "images/2016/06/01/dining/01BRONX-slide-EAFR/01BRONX-slide-EAFR-articleLarge.jpg", "subtype": "xlarge", "legacy": {"xlargewidth": "600", "xlargeheight": "401", "xlarge": "images/2016/06/01/dining/01BRONX-slide-EAFR/01BRONX-slide-EAFR-articleLarge.jpg"}, "type": "image"}, {"width": 75, "height": 75, "url": "images/2016/06/01/dining/01BRONX-slide-EAFR/01BRONX-slide-EAFR-thumbStandard.jpg", "subtype": "thumbnail", "legacy": {"thumbnail": "images/2016/06/01/dining/01BRONX-slide-EAFR/01BRONX-slide-EAFR-thumbStandard.jpg", "thumbnailwidth": "75", "thumbnailheight": "75"}, "type": "image"}], "section_name": "Food", "headline": {"main": "If You Brew It ..."}, "source": "The New York Times", "blog": [], "word_count": "15", "web_url": "http://www.nytimes.com/slideshow/2016/06/01/dining/coffee-bronx.html", "slideshow_credits": "Edwin J. Torres for The New York Times", "news_desk": "Food", "type_of_material": "Slideshow", "snippet": "In the South Bronx, the arrival of two high-end coffee shops sparks debate over gentrification.", "_id": "574db7a638f0d8334c662f8f", "abstract": null, "keywords": [{"rank": "1", "name": "subject", "value": "Coffeehouses", "is_major": "N"}, {"rank": "2", "name": "glocations", "value": "Bronx (NYC)", "is_major": "N"}, {"rank": "3", "name": "organizations", "value": "Birch Coffee Co", "is_major": "N"}, {"rank": "4", "name": "organizations", "value": "Filtered Coffee (Bronx, NY, Restaurant)", "is_major": "N"}]}