{"_id": "53e8329738f0d84035b5820c", "print_page": "22", "blog": [], "byline": null, "multimedia": [], "source": "The New York Times", "type_of_material": "Paid Death Notice", "news_desk": "Classified", "snippet": "JENCKS--Richard W.,retired CBS Broadcast Group President, dies at 93. See news story at MarinIJ.com....", "document_type": "article", "subsection_name": null, "word_count": "14", "headline": {"main": "Paid Notice: Deaths  JENCKS, RICHARD W."}, "lead_paragraph": "JENCKS--Richard W.,retired CBS Broadcast Group President, dies at 93. See news story at MarinIJ.com.", "slideshow_credits": null, "keywords": [{"name": "persons", "value": "JENCKS, RICHARD W."}], "pub_date": "2014-08-03T00:00:00Z", "section_name": "Paid Death Notices", "abstract": null, "web_url": "http://query.nytimes.com/gst/fullpage.html?res=9D07E1D7173AF930A3575BC0A9629D8B63"}