{"coordinates": {"longitude": 138.59995, "latitude": -34.92863}, "review_count": 0, "categories": [{"alias": "limos", "title": "Limos"}], "url": "https://www.yelp.com/biz/access-limo-adelaide?adjust_creative=92p07_JjKyriZTQxAXRiKQ&utm_campaign=yelp_api_v3&utm_medium=api_v3_business_lookup&utm_source=92p07_JjKyriZTQxAXRiKQ", "name": "Access Limo", "term": "hotels", "rating": 0.0, "photos": [], "is_closed": false, "is_claimed": false, "phone": "+61455515700", "image_url": "", "location": {"address2": "Adelaide CBD", "address3": "", "city": "Adelaide", "country": "AU", "address1": "Victoria Square", "state": "SA", "zip_code": "5000"}, "id": "access-limo-adelaide"}