{"_id": "534da00338f0d824d8a83b07", "print_page": null, "blog": [], "byline": {"person": [], "organization": "REUTERS", "original": "By REUTERS"}, "multimedia": [], "source": "Reuters", "type_of_material": "News", "news_desk": null, "snippet": "Toyota Motor Corp is set to post record growth for the year just ended - with a likely $10 billion surge in operating profit - but the mood at its HQ in Japan's prosperous automotive heartland is cautious as executives warn of a leaner year ahead....", "document_type": "article", "subsection_name": null, "word_count": "887", "headline": {"print_headline": "After Two Bumper Years, Toyota Braces for Shift to Slower Growth", "main": "After Two Bumper Years, Toyota Braces for Shift to Slower Growth"}, "lead_paragraph": "Toyota Motor Corp is set to post record growth for the year just ended - with a likely $10 billion surge in operating profit - but the mood at its HQ in Japan's prosperous automotive heartland is cautious as executives warn of a leaner year ahead.", "slideshow_credits": null, "keywords": [], "pub_date": "2014-04-15T17:08:33Z", "section_name": "Business Day", "abstract": null, "web_url": "http://www.nytimes.com/reuters/2014/04/15/business/15reuters-toyota-motor-outlook.html"}