{"url": "https://www.yelp.com/biz/bacon-boys-las-vegas?adjust_creative=92p07_JjKyriZTQxAXRiKQ&utm_campaign=yelp_api_v3&utm_medium=api_v3_business_lookup&utm_source=92p07_JjKyriZTQxAXRiKQ", "id": "bacon-boys-las-vegas", "location": {"state": "NV", "zip_code": "89109", "address2": "", "country": "US", "city": "Las Vegas", "address3": "", "address1": "3850 E Desert Inn Rd"}, "rating": 4.5, "photos": ["https://s3-media3.fl.yelpcdn.com/bphoto/E81uCU2-3WBOC1mBTuB6_A/o.jpg", "https://s3-media2.fl.yelpcdn.com/bphoto/hiXqiTJlvolA1R9uC_N8fQ/o.jpg", "https://s3-media2.fl.yelpcdn.com/bphoto/g_LjaaRLR77bUCSVNumIZQ/o.jpg"], "name": "Bacon Boys", "term": "restaurants", "phone": "+17022226696", "hours": [{"is_open_now": true, "open": [{"is_overnight": false, "end": "2200", "start": "0600", "day": 0}, {"is_overnight": false, "end": "2200", "start": "0600", "day": 1}, {"is_overnight": false, "end": "2200", "start": "0600", "day": 2}, {"is_overnight": false, "end": "2200", "start": "0600", "day": 3}, {"is_overnight": false, "end": "2200", "start": "0600", "day": 4}, {"is_overnight": false, "end": "2200", "start": "0600", "day": 5}, {"is_overnight": false, "end": "2200", "start": "0600", "day": 6}], "hours_type": "REGULAR"}], "coordinates": {"longitude": -115.0905569, "latitude": 36.1299863}, "categories": [{"alias": "tradamerican", "title": "American (Traditional)"}, {"alias": "burgers", "title": "Burgers"}, {"alias": "foodtrucks", "title": "Food Trucks"}], "is_closed": false, "image_url": "https://s3-media2.fl.yelpcdn.com/bphoto/E81uCU2-3WBOC1mBTuB6_A/o.jpg", "price": "$", "review_count": 35, "is_claimed": true}