{"location": {"address3": "", "address1": "91 H St NW", "country": "US", "state": "DC", "zip_code": "20001", "address2": "", "city": "Washington"}, "id": "chicken-rico-washington", "price": "$", "hours": [{"is_open_now": false, "hours_type": "REGULAR", "open": [{"start": "1030", "end": "2100", "is_overnight": false, "day": 0}, {"start": "1030", "end": "2100", "is_overnight": false, "day": 1}, {"start": "1030", "end": "2100", "is_overnight": false, "day": 2}, {"start": "1030", "end": "2100", "is_overnight": false, "day": 3}, {"start": "1030", "end": "2100", "is_overnight": false, "day": 4}, {"start": "1030", "end": "2100", "is_overnight": false, "day": 5}, {"start": "1100", "end": "2000", "is_overnight": false, "day": 6}]}], "review_count": 114, "photos": ["https://s3-media3.fl.yelpcdn.com/bphoto/5LfaVI9nhN_Mt3kD531m6A/o.jpg", "https://s3-media4.fl.yelpcdn.com/bphoto/_ZdxNZuQN559Ow_1vZy8UQ/o.jpg", "https://s3-media2.fl.yelpcdn.com/bphoto/a_jU1xbIq4QLNwKdaQILRA/o.jpg"], "is_claimed": true, "rating": 4.0, "is_closed": false, "image_url": "https://s3-media4.fl.yelpcdn.com/bphoto/5LfaVI9nhN_Mt3kD531m6A/o.jpg", "name": "Chicken Rico", "categories": [{"title": "Latin American", "alias": "latin"}, {"title": "Peruvian", "alias": "peruvian"}], "coordinates": {"latitude": 38.9003349, "longitude": -77.0119233}, "term": "restaurants", "phone": "+12028425007", "url": "https://www.yelp.com/biz/chicken-rico-washington?adjust_creative=92p07_JjKyriZTQxAXRiKQ&utm_campaign=yelp_api_v3&utm_medium=api_v3_business_lookup&utm_source=92p07_JjKyriZTQxAXRiKQ"}