{"_id": "543981c538f0d81c57108c55", "print_page": null, "blog": [], "byline": {"person": [], "organization": "THE ASSOCIATED PRESS", "original": "By THE ASSOCIATED PRESS"}, "multimedia": [], "source": "AP", "type_of_material": "News", "news_desk": "None", "snippet": "A 21-month-old girl is the first person in Michigan to die from the virus that has caused severe respiratory illness across the country, state health officials said Saturday....", "document_type": "article", "subsection_name": null, "word_count": "234", "headline": {"print_headline": "Michigan Toddler Dies From Enterovirus D68", "main": "Michigan Toddler Dies From Enterovirus D68"}, "lead_paragraph": "A 21-month-old girl is the first person in Michigan to die from the virus that has caused severe respiratory illness across the country, state health officials said Saturday.", "slideshow_credits": null, "keywords": [], "pub_date": "2014-10-11T15:13:27Z", "section_name": "U.S.", "abstract": null, "web_url": "http://www.nytimes.com/aponline/2014/10/11/us/ap-us-childrens-virus-michigan.html"}