{"_id": "54417ffe38f0d811e19d75ef", "print_page": null, "blog": [], "byline": {"person": [], "organization": "THE ASSOCIATED PRESS", "original": "By THE ASSOCIATED PRESS"}, "multimedia": [], "source": "AP", "type_of_material": "News", "news_desk": "None", "snippet": "A federal judge has ordered Wyoming to allow same-sex marriage but has stayed his decision so that the state can appeal if it wants....", "document_type": "article", "subsection_name": null, "word_count": "111", "headline": {"print_headline": "Federal Judge Overturns Wyoming Gay Marriage Ban", "main": "Federal Judge Overturns Wyoming Gay Marriage Ban"}, "lead_paragraph": "A federal judge has ordered Wyoming to allow same-sex marriage but has stayed his decision so that the state can appeal if it wants.", "slideshow_credits": null, "keywords": [], "pub_date": "2014-10-17T16:37:38Z", "section_name": "U.S.", "abstract": null, "web_url": "http://www.nytimes.com/aponline/2014/10/17/us/ap-us-gay-marriage-wyoming.html"}