{"_id": "539a2c2038f0d83101a1d041", "print_page": null, "blog": [], "byline": {"person": [], "organization": "REUTERS", "original": "By REUTERS"}, "multimedia": [], "source": "Reuters", "type_of_material": "News", "news_desk": null, "snippet": "A Sears employee in northern New York has died of injuries suffered when storage racks at the store collapsed and pinned him underneath, authorities said....", "document_type": "article", "subsection_name": null, "word_count": "163", "headline": {"print_headline": "Sears Worker in Upstate New York Dies After Shelves Collapse", "main": "Sears Worker in Upstate New York Dies After Shelves Collapse"}, "lead_paragraph": "A Sears employee in northern New York has died of injuries suffered when storage racks at the store collapsed and pinned him underneath, authorities said.", "slideshow_credits": null, "keywords": [], "pub_date": "2014-06-12T18:37:04Z", "section_name": "U.S.", "abstract": null, "web_url": "http://www.nytimes.com/reuters/2014/06/12/us/12reuters-usa-store-collapse.html"}