{"url": "https://www.yelp.com/biz/bobbys-bike-hike-tours-and-rentals-chicago?adjust_creative=92p07_JjKyriZTQxAXRiKQ&utm_campaign=yelp_api_v3&utm_medium=api_v3_business_lookup&utm_source=92p07_JjKyriZTQxAXRiKQ", "id": "bobbys-bike-hike-tours-and-rentals-chicago", "location": {"zip_code": "60611", "address2": "", "country": "US", "state": "IL", "city": "Chicago", "address1": "540 N Lake Shore Dr", "address3": ""}, "rating": 5.0, "photos": ["https://s3-media3.fl.yelpcdn.com/bphoto/56fKEHIJreDfbe7N6FAl7g/o.jpg", "https://s3-media3.fl.yelpcdn.com/bphoto/je1q9dHmCXwUM_H1I1kzHQ/o.jpg", "https://s3-media1.fl.yelpcdn.com/bphoto/NlEe1z_-69ByOyID15Cm4g/o.jpg"], "name": "Bobby's Bike Hike Tours & Rentals", "term": "attractions", "phone": "+13122459300", "hours": [{"is_open_now": false, "open": [{"is_overnight": false, "end": "2030", "start": "0830", "day": 0}, {"is_overnight": false, "end": "2030", "start": "0830", "day": 1}, {"is_overnight": false, "end": "2030", "start": "0830", "day": 2}, {"is_overnight": false, "end": "2030", "start": "0830", "day": 3}, {"is_overnight": false, "end": "2030", "start": "0830", "day": 4}, {"is_overnight": false, "end": "2030", "start": "0800", "day": 5}, {"is_overnight": false, "end": "2030", "start": "0800", "day": 6}], "hours_type": "REGULAR"}], "coordinates": {"longitude": -87.6151605702225, "latitude": 41.8924395839824}, "categories": [{"alias": "bikerentals", "title": "Bike Rentals"}, {"alias": "tours", "title": "Tours"}, {"alias": "bikes", "title": "Bikes"}], "is_closed": false, "image_url": "https://s3-media1.fl.yelpcdn.com/bphoto/56fKEHIJreDfbe7N6FAl7g/o.jpg", "price": "$$", "review_count": 373, "is_claimed": true}