{"coordinates": {"longitude": -0.16910415667953, "latitude": 51.48762124782}, "review_count": 34, "hours": [{"is_open_now": false, "open": [{"is_overnight": false, "end": "1700", "start": "1100", "day": 0}, {"is_overnight": false, "end": "1700", "start": "1100", "day": 1}, {"is_overnight": false, "end": "1700", "start": "1100", "day": 2}, {"is_overnight": false, "end": "1700", "start": "1100", "day": 3}, {"is_overnight": false, "end": "2000", "start": "1100", "day": 4}, {"is_overnight": false, "end": "2000", "start": "1100", "day": 5}, {"is_overnight": false, "end": "1700", "start": "1100", "day": 6}], "hours_type": "REGULAR"}], "categories": [{"title": "Vietnamese", "alias": "vietnamese"}, {"title": "Noodles", "alias": "noodles"}], "url": "https://www.yelp.com/biz/phat-phuc-noodle-bar-london?adjust_creative=92p07_JjKyriZTQxAXRiKQ&utm_campaign=yelp_api_v3&utm_medium=api_v3_business_lookup&utm_source=92p07_JjKyriZTQxAXRiKQ", "name": "Phat Phuc Noodle Bar", "term": "restaurants", "rating": 4.0, "photos": ["https://s3-media4.fl.yelpcdn.com/bphoto/RbSsNDwrNm-kVVcn38YmEw/o.jpg", "https://s3-media2.fl.yelpcdn.com/bphoto/HGArI2pb_qDrtTmxo2yKZQ/o.jpg", "https://s3-media4.fl.yelpcdn.com/bphoto/4LIF8GvlC6bJ1H-IwLmwSA/o.jpg"], "is_closed": false, "is_claimed": true, "phone": "+442073513843", "image_url": "https://s3-media3.fl.yelpcdn.com/bphoto/RbSsNDwrNm-kVVcn38YmEw/o.jpg", "location": {"address2": "", "address3": "", "zip_code": "SW3 6NT", "country": "GB", "address1": "151 Sydney Street", "state": "XGL", "city": "London"}, "price": "\u00a3", "id": "phat-phuc-noodle-bar-london"}