{"_id": "5446cb6e38f0d850b0934f65", "print_page": null, "blog": [], "byline": {"person": [], "organization": "THE ASSOCIATED PRESS", "original": "By THE ASSOCIATED PRESS"}, "multimedia": [], "source": "AP", "type_of_material": "News", "news_desk": "None", "snippet": "Tony Award-winner Victoria Clark has joined the Broadway-bound musical \"Gigi\" playing a grandmother....", "document_type": "article", "subsection_name": null, "word_count": "122", "headline": {"print_headline": "Victoria Clark Joins the Cast of Musical 'Gigi'", "main": "Victoria Clark Joins the Cast of Musical 'Gigi'"}, "lead_paragraph": "Tony Award-winner Victoria Clark has joined the Broadway-bound musical \"Gigi\" playing a grandmother.", "slideshow_credits": null, "keywords": [], "pub_date": "2014-10-21T17:04:30Z", "section_name": "Arts", "abstract": null, "web_url": "http://www.nytimes.com/aponline/2014/10/21/arts/ap-us-theater-victoria-clark.html"}